integration_tests/__init__.py
integration_tests/abnormal_state.json
integration_tests/acceptance.py
integration_tests/catalog.json
integration_tests/configured_catalog.json
integration_tests/invalid_config.json
integration_tests/sample_config.json
integration_tests/sample_state.json
source_dv_360/__init__.py
source_dv_360/fields.py
source_dv_360/run.py
source_dv_360/source.py
source_dv_360/spec.json
source_dv_360/streams.py
source_dv_360/queries/query_template.json
source_dv_360/schemas/audience_composition.json
source_dv_360/schemas/floodlight.json
source_dv_360/schemas/reach.json
source_dv_360/schemas/standard.json
source_dv_360/schemas/unique_reach_audience.json
airbyte_source_dv_360-0.1.0.dist-info/METADATA
airbyte_source_dv_360-0.1.0.dist-info/WHEEL
airbyte_source_dv_360-0.1.0.dist-info/entry_points.txt
airbyte_source_dv_360-0.1.0.dist-info/top_level.txt
airbyte_source_dv_360-0.1.0.dist-info/RECORD
