Metadata-Version: 2.1
Name: airbyte-source-dv-360
Version: 0.1.0
Summary: Source implementation for Display & Video 360.
Author: Airbyte
Author-email: contact@airbyte.io
Requires-Dist: airbyte-cdk ~=0.1
Requires-Dist: google-api-python-client
Provides-Extra: tests
Requires-Dist: requests-mock ~=1.9.3 ; extra == 'tests'
Requires-Dist: pytest ~=6.1 ; extra == 'tests'
Requires-Dist: pytest-mock ; extra == 'tests'
